Metadata-Version: 2.1
Name: xpath-perfomance
Version: 0.0.1
Summary: Wrapper for Selenium to make it more easy and efficient to use
Author: Parceiro do Contador
Author-email: parceiro@parceirodocontador.com.br
License: Code Distribution License
Keywords: selenium xpath
License-File: LICENCE
